<Publish>
	<ModId Value="76922" />
	<DisplayName Value="Terraform Hardening" />
	<ShortDescription
		Value="Makes terraforming cost something, you can control the cost from settings" />
	<LongDescription>
		<![CDATA[
Terraforming has a price.

You can control the price from the settings menu.
		]]>
	</LongDescription>
	<Thumbnail Value="Properties/Thumbnail.png" />
	<Screenshot Value="Properties/500k-with-multiplier2-texts.jpg" />
	<Tag Value="" />
	<ForumLink Value="" />
	<ModVersion Value="0.1.9" />
	<GameVersion Value="1.*" />
	<Dependency Id="" />
	<ChangeLog>
		Renamed to Terraform Hardening, as CO removed subsidies.
	</ChangeLog>
	<ExternalLink Type="github" Url="https://github.com/Ciantic/TerraformHardening" />
</Publish>